CHANGELOG
LICENSE
MANIFEST.in
README.rst
setup.py
django_happenings.egg-info/PKG-INFO
django_happenings.egg-info/SOURCES.txt
django_happenings.egg-info/dependency_links.txt
django_happenings.egg-info/not-zip-safe
django_happenings.egg-info/requires.txt
django_happenings.egg-info/top_level.txt
happenings/__init__.py
happenings/admin.py
happenings/managers.py
happenings/models.py
happenings/urls.py
happenings/views.py
happenings/migrations/0001_initial.py
happenings/migrations/__init__.py
happenings/south_migrations/0001_initial.py
happenings/south_migrations/0002_auto__add_cancellation.py
happenings/south_migrations/__init__.py
happenings/static/happenings/css/calendar.css
happenings/static/happenings/js/calendar.js
happenings/templates/happenings/base.html
happenings/templates/happenings/event_day_list.html
happenings/templates/happenings/event_detail.html
happenings/templates/happenings/event_month_list.html
happenings/templates/happenings/middle.html
happenings/templates/happenings/partials/event_list.html
happenings/templates/happenings/partials/happening_events.html
happenings/templates/happenings/partials/upcoming_events.html
happenings/templates/happenings/partials/calendar/day_cell.html
happenings/templates/happenings/partials/calendar/day_noday_cell.html
happenings/templates/happenings/partials/calendar/mini_day_cell.html
happenings/templates/happenings/partials/calendar/mini_popover.html
happenings/templates/happenings/partials/calendar/month_table.html
happenings/templates/happenings/partials/calendar/popover.html
happenings/templatetags/__init__.py
happenings/templatetags/happenings_tags.py
happenings/templatetags/weekday.py
happenings/utils/__init__.py
happenings/utils/calendars.py
happenings/utils/common.py
happenings/utils/displays.py
happenings/utils/handlers.py
happenings/utils/mixins.py
happenings/utils/next_event.py
happenings/utils/upcoming.py
tests/__init__.py
tests/manage.py
tests/settings.py
tests/urls.py
tests/integration_tests/__init__.py
tests/integration_tests/event_factory.py
tests/integration_tests/test_categories.py
tests/integration_tests/test_chunk.py
tests/integration_tests/test_chunk_biweekly_repeat.py
tests/integration_tests/test_chunk_monthly_repeat.py
